LICENSE.txt
MANIFEST.in
NOTICE.txt
README.md
requirements.txt
setup.cfg
setup.py
sendsafely/Package.py
sendsafely/Progress.py
sendsafely/SendSafely.py
sendsafely/__init__.py
sendsafely/exceptions.py
sendsafely/utilities.py
sendsafely.egg-info/PKG-INFO
sendsafely.egg-info/SOURCES.txt
sendsafely.egg-info/dependency_links.txt
sendsafely.egg-info/requires.txt
sendsafely.egg-info/top_level.txt
sendsafely/pgpy/__init__.py
sendsafely/pgpy/_curves.py
sendsafely/pgpy/constants.py
sendsafely/pgpy/decorators.py
sendsafely/pgpy/errors.py
sendsafely/pgpy/pgp.py
sendsafely/pgpy/symenc.py
sendsafely/pgpy/types.py
sendsafely/pgpy/packet/__init__.py
sendsafely/pgpy/packet/fields.py
sendsafely/pgpy/packet/packets.py
sendsafely/pgpy/packet/types.py
sendsafely/pgpy/packet/subpackets/__init__.py
sendsafely/pgpy/packet/subpackets/signature.py
sendsafely/pgpy/packet/subpackets/types.py
sendsafely/pgpy/packet/subpackets/userattribute.py