Metadata-Version: 2.1
Name: sendsafely
Version: 1.0.9.6
Summary: The SendSafely Client API allows programmatic access to SendSafely and provides a layer of abstraction from our REST API, which requires developers to perform several complex tasks in a correct manner.
Home-page: https://github.com/SendSafely/Python-Client-API
Author: SendSafely
Author-email: support@sendsafely.com
License: Apache License Version 2.0
Classifier: Development Status :: 5 - Production/Stable
Classifier: Intended Audience :: Developers
Classifier: Topic :: Software Development :: Libraries :: Application Frameworks
Classifier: Programming Language :: Python :: 3
Classifier: License :: OSI Approved :: Apache Software License
Requires-Python: >=3
License-File: LICENSE.txt
License-File: NOTICE.txt
